castmail2list/REUSE.toml
castmail2list/__init__.py
castmail2list/app.py
castmail2list/babel.cfg
castmail2list/config.py
castmail2list/forms.py
castmail2list/gunicorn.conf.py
castmail2list/imap_worker.py
castmail2list/mailer.py
castmail2list/migrations/README
castmail2list/migrations/alembic.ini
castmail2list/migrations/env.py
castmail2list/migrations/script.py.mako
castmail2list/migrations/versions/000000000000_initial_schema.py
castmail2list/migrations/versions/567ebef5513b_subscriber_add_bounce_column_to_count_.py
castmail2list/models.py
castmail2list/seed_default.json
castmail2list/seed_default.json.license
castmail2list/seeder.py
castmail2list/services.py
castmail2list/static/css/fontawesome-all.min.css
castmail2list/static/img/apple-touch-icon.png
castmail2list/static/img/favicon-96x96.png
castmail2list/static/img/favicon.ico
castmail2list/static/img/favicon.svg
castmail2list/static/img/site.webmanifest
castmail2list/static/img/web-app-manifest-192x192.png
castmail2list/static/img/web-app-manifest-512x512.png
castmail2list/static/js/themeToggle.js
castmail2list/static/scss/main.scss
castmail2list/static/scss/pico/_index.scss
castmail2list/static/scss/pico/_settings.scss
castmail2list/static/scss/pico/colors/_index.scss
castmail2list/static/scss/pico/colors/utilities/_background-colors.scss
castmail2list/static/scss/pico/colors/utilities/_colors.scss
castmail2list/static/scss/pico/colors/utilities/_css-vars.scss
castmail2list/static/scss/pico/colors/utilities/_index.scss
castmail2list/static/scss/pico/colors/utilities/_settings.scss
castmail2list/static/scss/pico/colors/utilities/_utils.scss
castmail2list/static/scss/pico/components/_accordion.scss
castmail2list/static/scss/pico/components/_card.scss
castmail2list/static/scss/pico/components/_dropdown.scss
castmail2list/static/scss/pico/components/_group.scss
castmail2list/static/scss/pico/components/_loading.scss
castmail2list/static/scss/pico/components/_modal.scss
castmail2list-0.5.2.dist-info/METADATA
castmail2list-0.5.2.dist-info/WHEEL
castmail2list-0.5.2.dist-info/entry_points.txt
castmail2list-0.5.2.dist-info/licenses/LICENSE
castmail2list-0.5.2.dist-info/licenses/LICENSES/Apache-2.0.txt
castmail2list-0.5.2.dist-info/licenses/LICENSES/BSD-2-Clause.txt
castmail2list-0.5.2.dist-info/licenses/LICENSES/CC-BY-4.0.txt
castmail2list-0.5.2.dist-info/licenses/LICENSES/CC0-1.0.txt
castmail2list-0.5.2.dist-info/licenses/LICENSES/MIT.txt
castmail2list-0.5.2.dist-info/licenses/LICENSES/OFL-1.1.txt
castmail2list-0.5.2.dist-info/RECORD
